harmonization/__init__.py
harmonization/common/__init__.py
harmonization/common/blur.py
harmonization/common/clickme_dataset.py
harmonization/evaluation/__init__.py
harmonization/evaluation/clickme.py
harmonization/evaluation/metrics.py
harmonization/models/__init__.py
harmonization/models/convnext.py
harmonization/models/efficientnetb0.py
harmonization/models/levit.py
harmonization/models/maxvit.py
harmonization/models/preprocess.py
harmonization/models/resnet50.py
harmonization/models/vgg16.py
harmonization/models/vit.py
harmonization/training/__init__.py
harmonization/training/loss.py
harmonization/training/pyramid.py
tests/__init__.py
tests/utils.py
tests/common/__init__.py
tests/common/test_clickme_dataset.py
tests/evaluation/__init__.py
tests/evaluation/test_metrics.py
tests/evaluation/test_tf_evaluation.py
tests/models/__init__.py
tests/models/test_bucket.py
tests/training/__init__.py
tests/training/test_loss.py
Harmonization-0.0.9.dist-info/LICENSE
Harmonization-0.0.9.dist-info/METADATA
Harmonization-0.0.9.dist-info/WHEEL
Harmonization-0.0.9.dist-info/top_level.txt
Harmonization-0.0.9.dist-info/RECORD
